{
  "users": [
    {
      "id": 1,
      "first_name": "Susie",
      "last_name": "Stanley",
      "image": "https://res.cloudinary.com/dllowdq2w/image/upload/v1636436400/susie2_vzbbqq.png",
      "email": "me@me.com",
      "last_visit": 1644100267945
    },
    {
      "first_name": "Taylor",
      "last_name": "Smith",
      "email": "taylor@email.com",
      "image": "https://res.cloudinary.com/dllowdq2w/image/upload/v1635548970/wendy_fampug.png",
      "last_visit": 1635611882958,
      "id": 2
    },
    {
      "id": 3,
      "first_name": "Testy",
      "last_name": "Tester",
      "image": "",
      "email": "test@test.com",
      "last_visit": 1643859602257
    },
    {
      "first_name": "Jane",
      "last_name": "Doe",
      "email": "jane@jane.com",
      "image": "",
      "last_visit": 1643921671899,
      "id": 4
    },
    {
      "first_name": "myfirstname",
      "last_name": "mylastname",
      "email": "name@name.com",
      "image": "",
      "last_visit": 1644174477678,
      "id": 5
    }
  ],
  "recipes": [
    {
      "userId": 1,
      "name": "Sugar Cookies",
      "categoryId": "2",
      "description": "Summary will show a maximum character count of 120 and will make it show 3 dots at the end if it exceeds the amount specified by the code in recipe card",
      "instructions": "Bake cake then eat it Bake cake then eat it Bake cake then eat it Bake cake then eat it Bake cake then eat it Bake cake then eat it Bake cake then eat it Bake cake then eat it Bake cake then eat it Bake cake then eat it Bake cake then eat it Bake cake then eat it Bake cake then eat it Bake cake then eat it Bake cake then eat it Bake cake then eat it Bake cake then eat it Bake cake then eat it Bake cake then eat it Bake cake then eat it Bake cake then eat it Bake cake then eat it Bake cake then eat it",
      "isFave": true,
      "ratingId": 6,
      "prep": "44",
      "cook": "44",
      "servings": "4",
      "date": 1644531385380,
      "id": 1
    },
    {
      "userId": 1,
      "name": "Chocolate Cake",
      "categoryId": 3,
      "description": "Summary will show a maximum character count of 120 and will make it show 3 dots at the end if it exceeds the amount specified. Summary will show a maximum character count of 120 and will make it show 3 dots at the end if it exceeds that amount. Summary will show a maximum character count of 120 and will make it show 3 dots at the end if it exceeds that amount. add some more words to get up to five hundred words to see what it looks like just keep typing and don't worry about what it says we just",
      "instructions": "Bake cake then eat it",
      "isFave": false,
      "ratingId": 5,
      "prep": "20",
      "cook": "30",
      "servings": "6",
      "date": 1644532258934,
      "id": 2
    },
    {
      "userId": 1,
      "name": "Birthday Cupcakes",
      "categoryId": 4,
      "description": "Summary will show a maximum character count of 120 and will make it show 3 dots at the end if it exceeds the amount specified by the code in recipe card",
      "instructions": "Summary will show a maximum character count of 120 and will make it show 3 dots at the end if it exceeds the amount specified. Summary will show a maximum character count of 120 and will make it show 3 dots at the end if it exceeds that amount. Summary will show a maximum character count of 120 and will make it show 3 dots at the end if it exceeds that amount. add some more words to get up to five hundred words to see what it looks like just keep typing and don't worry about what it says we just  ",
      "isFave": false,
      "ratingId": 6,
      "prep": "20",
      "cook": "30",
      "servings": "6",
      "date": 1644532511303,
      "id": 3
    },
    {
      "userId": 1,
      "name": "Banana Muffins",
      "categoryId": 5,
      "description": "Summary will show a maximum character count of 120 and will make it show 3 dots at the end if it exceeds the amount specified by the code in recipe card",
      "instructions": "Bake cake then eat it, Bake cake then eat it, Bake cake then eat it",
      "isFave": false,
      "ratingId": 5,
      "prep": "20",
      "cook": "30",
      "servings": "6",
      "date": 1644533200314,
      "id": 4
    },
    {
      "userId": 1,
      "name": "Fudge Brownies",
      "categoryId": 6,
      "description": "Summary will show a maximum character count of 120 and will make it show 3 dots at the end if it exceeds the amount specified by the code in recipe card",
      "instructions": "Bake cake then eat it",
      "isFave": false,
      "ratingId": 5,
      "prep": "20",
      "cook": "30",
      "servings": "6",
      "date": 1644533367448,
      "id": 5
    },
    {
      "userId": 1,
      "name": "Granola Bars",
      "categoryId": 7,
      "description": "Summary will show a maximum character count of 120 and will make it show 3 dots at the end if it exceeds the amount specified by the code in recipe card",
      "instructions": "Bake cake then eat it",
      "isFave": false,
      "ratingId": 6,
      "prep": "20",
      "cook": "30",
      "servings": "6",
      "date": 1644530478479,
      "id": 6
    },
    {
      "userId": 1,
      "name": "Gingerbread",
      "categoryId": 8,
      "description": "Summary will show a maximum character count of 120 and will make it show 3 dots at the end if it exceeds the amount specified by the code in recipe card",
      "instructions": "Bake cake then eat it",
      "isFave": false,
      "ratingId": 3,
      "prep": "20",
      "cook": "30",
      "servings": "6",
      "date": 1644542128341,
      "id": 7
    },
    {
      "userId": 1,
      "name": "Zucchini Bread",
      "categoryId": 9,
      "description": "Summary will show a maximum character count of 120 and will make it show 3 dots at the end if it exceeds the amount specified by the code in recipe card",
      "instructions": "Bake cake then eat it",
      "isFave": false,
      "ratingId": 6,
      "prep": "20",
      "cook": "30",
      "servings": "6",
      "date": 1644542461813,
      "id": 8
    },
    {
      "userId": 1,
      "name": "Apple Pie",
      "categoryId": 10,
      "description": "Summary will show a maximum character count of 120 and will make it show 3 dots at the end if it exceeds the amount specified by the code in recipe card",
      "instructions": "Bake cake then eat it",
      "isFave": false,
      "ratingId": 3,
      "prep": "20",
      "cook": "30",
      "servings": "6",
      "date": 1644542562689,
      "id": 9
    },
    {
      "userId": 1,
      "name": "Cookie Icing",
      "categoryId": 11,
      "description": "Summary will show a maximum character count of 120 and will make it show 3 dots at the end if it exceeds the amount specified by the code in recipe card",
      "instructions": "Mmmm I love me some cookie icing",
      "isFave": false,
      "ratingId": 5,
      "prep": "20",
      "cook": "30",
      "servings": "6",
      "date": 1644542009421,
      "id": 10
    },
    {
      "userId": 1,
      "name": "Bon Bons",
      "categoryId": 12,
      "description": "Summary will show a maximum character count of 120 and will make it show 3 dots at the end if it exceeds the amount specified by the code in recipe card",
      "instructions": "Bake cake then eat it",
      "isFave": false,
      "ratingId": 3,
      "prep": "20",
      "cook": "30",
      "servings": "6",
      "date": 1644545766550,
      "id": 11
    },
    {
      "userId": 1,
      "name": "Sprinkle Donuts",
      "categoryId": 13,
      "description": "Just like an old-fashioned donut,but better because who doesn't love sprinkles? These babies are perfect for when you are in the mood for a sweet, satisfying treat any time of day.",
      "instructions": "Instructions Checklist\nStep 1\nPreheat the oven to 350 degrees F (175 degrees C). Grease donut pans well.\n\nStep 2\nSift flour, sugar, cocoa, baking powder, and salt together into a large bowl.\n\nStep 3\nWhisk milk, egg, butter, oil, and 2 teaspoons vanilla extract together in a small bowl. Stir into flour mixture until just combined.\n\nStep 4\nSpoon batter into the prepared donut pans, filling each well 3/4 full.\n\nStep 5\nBake in the preheated oven until a toothpick inserted into a donut comes out clean, about 10 minutes. Remove from the oven and let cool for about 5 minutes; tap donuts out onto a sheet pan.\n\nStep 6\nCombine confectioners' sugar, hot water, and remaining vanilla extract in a bowl to make the glaze.\n\nStep 7\nPlace parchment paper under a wire cooling rack. Transfer cooled donuts to the rack and coat in glaze, letting excess drip onto parchment paper; coat the donuts a second time if desired.",
      "isFave": false,
      "ratingId": 4,
      "prep": "20",
      "cook": "30",
      "servings": "6",
      "date": 1644554598499,
      "id": 12
    },
    {
      "userId": 1,
      "name": "Cinnamon Rolls",
      "categoryId": 14,
      "description": "Summary will show a maximum character count of 120 and will make it show 3 dots at the end if it exceeds the amount specified by the code in recipe card",
      "instructions": "Bake cake then eat it",
      "isFave": false,
      "ratingId": 5,
      "prep": "20",
      "cook": "30",
      "servings": "6",
      "date": 1644545552318,
      "id": 13
    },
    {
      "userId": 1,
      "name": "Coated Strawberries",
      "categoryId": 15,
      "description": "Summary will show a maximum character count of 120 and will make it show 3 dots at the end if it exceeds the amount specified by the code in recipe card",
      "instructions": "Bake cake then eat it",
      "isFave": true,
      "ratingId": 5,
      "prep": "20",
      "cook": "30",
      "servings": "6",
      "date": 1644542429932,
      "id": 14
    },
    {
      "userId": 1,
      "name": "Ginger Cookies",
      "categoryId": 2,
      "description": "Summary will show a maximum character count of 120 and will make it show 3 dots at the end if it exceeds the amount specified by the code in recipe card",
      "instructions": "I love to make these cookies at Christmas time",
      "isFave": true,
      "ratingId": 5,
      "prep": "20",
      "cook": "30",
      "servings": "6",
      "date": 1644532193830,
      "id": 15
    },
    {
      "userId": 1,
      "name": "Strawberry Cake",
      "categoryId": 3,
      "description": "Summary will show a maximum character count of 120 and will make it show 3 dots at the end if it exceeds the amount specified in the code on recipe card",
      "instructions": "Bake cake then eat it",
      "isFave": false,
      "ratingId": 4,
      "prep": "20",
      "cook": "30",
      "servings": "6",
      "date": 1644549533255,
      "id": 16
    },
    {
      "userId": 1,
      "name": "Iced Lemon Cupcakes",
      "categoryId": 4,
      "description": "Summary will show a maximum character count of 120 and will make it show 3 dots at the end if it exceeds the amount specified in the code on recipe card",
      "instructions": "Bake cake then eat it",
      "isFave": false,
      "ratingId": 5,
      "prep": "20",
      "cook": "30",
      "servings": "6",
      "date": 1644532788474,
      "id": 17
    },
    {
      "userId": 1,
      "name": "Bran Muffins",
      "categoryId": 5,
      "description": "Summary will show a maximum character count of 120 and will make it show 3 dots at the end if it exceeds the amount specified in the code on recipe card",
      "instructions": "Bake cake then eat it",
      "isFave": false,
      "ratingId": 2,
      "prep": "20",
      "cook": "30",
      "servings": "6",
      "date": 1644533088415,
      "id": 18
    },
    {
      "userId": 1,
      "name": "Blondies",
      "categoryId": 6,
      "description": "Summary will show a maximum character count of 120 and will make it show 3 dots at the end if it exceeds the amount specified in the code on recipe card",
      "instructions": "Bake cake then eat it",
      "isFave": true,
      "ratingId": 5,
      "prep": "20",
      "cook": "30",
      "servings": "6",
      "date": 1644540031214,
      "id": 19
    },
    {
      "userId": 1,
      "name": "Lemon Bars",
      "categoryId": 7,
      "description": "Summary will show a maximum character count of 120 and will make it show 3 dots at the end if it exceeds the amount specified in the code on recipe card",
      "instructions": "Bake cake then eat it",
      "isFave": true,
      "ratingId": 3,
      "prep": "20",
      "cook": "30",
      "servings": "6",
      "date": 1644530431734,
      "id": 20
    },
    {
      "userId": 1,
      "name": "Bourbon Balls",
      "categoryId": 8,
      "description": "Summary will show a maximum character count of 120 and will make it show 3 dots at the end if it exceeds the amount specified in the code on recipe card",
      "instructions": "Bake cake then eat it",
      "isFave": true,
      "ratingId": 1,
      "prep": "20",
      "cook": "30",
      "servings": "6",
      "date": 1644545846910,
      "id": 21
    },
    {
      "userId": 1,
      "name": "Blueberry Loaf",
      "categoryId": 9,
      "description": "Summary will show a maximum character count of 120 and will make it show 3 dots at the end if it exceeds the amount specified in the code on recipe card",
      "instructions": "Bake cake then eat it",
      "isFave": false,
      "ratingId": 5,
      "prep": "20",
      "cook": "30",
      "servings": "6",
      "date": 1644545906413,
      "id": 22
    },
    {
      "userId": 1,
      "name": "Cherry Pie",
      "categoryId": 10,
      "description": "Summary will show a maximum character count of 120 and will make it show 3 dots at the end if it exceeds the amount specified in the code on recipe card",
      "instructions": "Bake cake then eat it",
      "isFave": false,
      "ratingId": 5,
      "prep": "20",
      "cook": "30",
      "servings": "6",
      "date": 1644545933087,
      "id": 23
    },
    {
      "userId": 1,
      "name": "Creamcheese Frosting",
      "categoryId": 11,
      "description": "Summary will show a maximum character count of 120 and will make it show 3 dots at the end if it exceeds the amount specified in the code on recipe card",
      "instructions": "Bake cake then eat it",
      "isFave": false,
      "ratingId": 5,
      "prep": "20",
      "cook": "30",
      "servings": "6",
      "date": 1644545972576,
      "id": 24
    },
    {
      "userId": 1,
      "name": "Fudge",
      "categoryId": 12,
      "description": "Summary will show a maximum character count of 120 and will make it show 3 dots at the end if it exceeds the amount specified in the code on recipe card",
      "instructions": "Bake cake then eat it",
      "isFave": false,
      "ratingId": 1,
      "prep": "20",
      "cook": "30",
      "servings": "6",
      "date": 1644546558412,
      "id": 25
    },
    {
      "userId": 1,
      "name": "Cronut",
      "categoryId": 13,
      "description": "Summary will show a maximum character count of 120 and will make it show 3 dots at the end if it exceeds the amount specified in the code on recipe card",
      "instructions": "Bake cake then eat it",
      "isFave": true,
      "ratingId": 5,
      "prep": "20",
      "cook": "30",
      "servings": "6",
      "date": 1644546722957,
      "id": 26
    },
    {
      "userId": 1,
      "name": "Pumpkin Roll",
      "categoryId": 14,
      "description": "Summary will show a maximum character count of 120 and will make it show 3 dots at the end if it exceeds the amount specified in the code on recipe card",
      "instructions": "Bake cake then eat it",
      "isFave": false,
      "ratingId": 4,
      "prep": "20",
      "cook": "30",
      "servings": "6",
      "date": 1644546758712,
      "id": 27
    },
    {
      "userId": 1,
      "name": "Fruity Cheesecake",
      "categoryId": 15,
      "description": "Summary will show a maximum character count of 120 and will make it show 3 dots at the end if it exceeds the amount specified in the code on recipe card",
      "instructions": "Bake cake then eat it",
      "isFave": true,
      "ratingId": 6,
      "prep": "20",
      "cook": "30",
      "servings": "6",
      "date": 1644549494906,
      "id": 28
    },
    {
      "userId": 1,
      "name": "Snickerdoodles",
      "categoryId": "2",
      "description": "I love these sweet cinnamon treats. Great with a big mug of milk on a cold snowy day! I like to use light brown sugar on top.",
      "instructions": "Bake all the cookies then eat all the cookies!",
      "isFave": true,
      "ratingId": 6,
      "prep": "3",
      "cook": "3",
      "servings": "3",
      "date": 1644531418579,
      "id": 29
    },
    {
      "userId": 1,
      "name": "Blueberry Muffins",
      "categoryId": 5,
      "description": "I love a hot warm muffin straight out of the oven smothered in creamy butter! These are great warm and cold and contain lots of antioxidants too.",
      "instructions": "Bake the muffins then eat the muffins! YUM!",
      "isFave": true,
      "ratingId": 3,
      "prep": "3",
      "cook": "3",
      "servings": "3",
      "date": 1644531063935,
      "id": 30
    },
    {
      "userId": 1,
      "name": "S'mores Bars",
      "categoryId": 7,
      "description": "This recipe is a new twist on the old tradition of everyone's campfire favorite! This brings back great memories of my childhood. Back when days were simpler and life was slower.",
      "instructions": "Put all ingredients together and shove it in your mouth",
      "isFave": false,
      "ratingId": 3,
      "prep": "20",
      "cook": "10",
      "servings": "6",
      "date": 1644540365075,
      "id": 31
    },
    {
      "userId": 1,
      "name": "Croissants",
      "categoryId": 15,
      "description": "These soft buttery french \"kwasson\" will melt in your mouth. The combination of textures between the flakey pastry and buttery smoothness transport me to Paris.",
      "instructions": "For the croissant dough: In the bowl of your stand mixer, combine the flour, yeast, sugar and salt, then whisk together. Add 2 tablespoons of room temperature butter and beat with the paddle attachment. Mix on low speed until combined and the butter is no longer visible. Add the milk. Mix on low speed until the dough comes together, then switch to the dough hook. Knead on medium-high until the dough comes together into a smooth but still slightly loose ball, about 5 minutes. Remove from the mixer, then pat into a rectangle and wrap in plastic wrap. Let rest in the refrigerator for 1 hour.",
      "isFave": false,
      "ratingId": 4,
      "prep": "30",
      "cook": "30",
      "servings": "6",
      "date": 1644555076083,
      "id": 32
    },
    {
      "userId": 1,
      "name": "Hazelnut Balls",
      "categoryId": 12,
      "description": "These classic chocolate candies are a hit everytime. Chopped hazelnuts coated in chocolate on the outside and delicious hazelnut creme on the inside. Time consuming process but worth every minute once you taste them.",
      "instructions": "Roll into balls then use fork to dip in chocolate, roll in nuts, then dip again in chocolate. Messy but tasty!",
      "isFave": false,
      "ratingId": 4,
      "prep": "45",
      "cook": "60",
      "servings": "24",
      "date": 1644548368869,
      "id": 33
    },
    {
      "userId": 1,
      "name": "Peach Turnover",
      "categoryId": "10",
      "description": "Yummy in my tummy. You can make these with apple, cherry, strawberry-rhubarb, peach... the options are endless. Add a nice glaze on top for the finishing touch!",
      "instructions": "Bake the turnovers then eat them all at once!",
      "isFave": false,
      "ratingId": 6,
      "prep": "45",
      "cook": "30",
      "servings": "12",
      "date": 1644550513230,
      "id": 34
    },
    {
      "userId": 1,
      "name": "Strawberry Cupcakes",
      "categoryId": 4,
      "description": "Yummy strawberry flavors burst out from every bite of these delicious cuppy-cakes! Don't leave them out because they will be consumed very quickly. Use cream cheese frosting for a next level experience.",
      "instructions": "Bake the cupcakes then eat the cupcakes",
      "isFave": false,
      "ratingId": 5,
      "prep": "30",
      "cook": "30",
      "servings": "12",
      "date": 1644549413746,
      "id": 35
    },
    {
      "userId": 1,
      "name": "Chocolate Chip Cookies",
      "categoryId": 2,
      "description": "Classic boring chocolate chip cookie that everyone loves and I don't know why :) Even though there are so many other choices that are far superior, this seems to be the crowd-pleaser. If you aren't being adventurous, this is your cookie :)",
      "instructions": "Mix together all the ingredients then make balls and arrange them on cookie sheet and bake",
      "isFave": false,
      "ratingId": 6,
      "prep": "30",
      "cook": "30",
      "servings": "24",
      "date": 1644553288458,
      "id": 36
    }
  ],
  "categories": [
    {
      "name": "All Recipes",
      "image": "140cakeslice.png",
      "id": 1
    },
    {
      "name": "Cookies",
      "image": "140cookie.png",
      "id": 2
    },
    {
      "name": "Cakes",
      "image": "140cakefull.png",
      "id": 3
    },
    {
      "name": "Cupcakes",
      "image": "140cupcake.png",
      "id": 4
    },
    {
      "name": "Muffins",
      "image": "140muffin.png",
      "id": 5
    },
    {
      "name": "Brownies",
      "image": "140brownie.png",
      "id": 6
    },
    {
      "name": "Bars",
      "image": "140bar.png",
      "id": 7
    },
    {
      "name": "Holidays",
      "image": "140holiday.png",
      "id": 8
    },
    {
      "name": "Breads",
      "image": "140bread.png",
      "id": 9
    },
    {
      "name": "Pies",
      "image": "140pie.png",
      "id": 10
    },
    {
      "name": "Frosting",
      "image": "140frosting.png",
      "id": 11
    },
    {
      "name": "Candy",
      "image": "140candy.png",
      "id": 12
    },
    {
      "name": "Donuts",
      "image": "140donut.png",
      "id": 13
    },
    {
      "name": "Rolls ",
      "image": "140roll.png",
      "id": 14
    },
    {
      "name": "Other",
      "image": "140other.png",
      "id": 15
    }
  ],
  "measurements": [
    {
      "name": "tsp",
      "id": 1
    },
    {
      "name": "tbsp",
      "id": 2
    },
    {
      "name": "cup",
      "id": 3
    },
    {
      "name": "cups",
      "id": 4
    },
    {
      "name": "pinch",
      "id": 5
    },
    {
      "name": "dash",
      "id": 6
    },
    {
      "name": "pint",
      "id": 7
    },
    {
      "name": "quart",
      "id": 8
    },
    {
      "name": "stick",
      "id": 9
    },
    {
      "name": "box",
      "id": 10
    },
    {
      "name": "boxes",
      "id": 11
    },
    {
      "name": "can(s)",
      "id": 11
    },
    {
      "name": "oz",
      "id": 12
    },
    {
      "name": "liter",
      "id": 13
    },
    {
      "name": "ml",
      "id": 14
    },
    {
      "name": "gram(s)",
      "id": 15
    },
    {
      "name": "piece(s)",
      "id": 16
    },
    {
      "name": "bag(s)",
      "id": 17
    },
    {
      "name": "whole",
      "id": 18
    },
    {
      "name": "half",
      "id": 19
    },
    {
      "name": "third",
      "id": 20
    },
    {
      "name": "quarter",
      "id": 21
    },
    {
      "name": "lb",
      "id": 22
    },
    {
      "name": "kg",
      "id": 23
    },
    {
      "name": "package",
      "id": 24
    },
    {
      "name": "large",
      "id": 25
    },
    {
      "name": "medium",
      "id": 26
    },
    {
      "name": "small",
      "id": 27
    }
  ],
  "ingredients": [
    {
      "recipeId": 1,
      "label": "sugar",
      "amount": 2,
      "measurement": "tbsp",
      "id": 1
    },
    {
      "recipeId": 1,
      "label": "butter",
      "amount": 2,
      "measurement": "cups",
      "id": 2
    },
    {
      "recipeId": 1,
      "label": "flour",
      "amount": 2,
      "measurement": "tbsp",
      "id": 3
    },
    {
      "amount": "3",
      "measurement": "cups",
      "label": "vinegar",
      "recipeId": "1",
      "id": 4
    },
    {
      "label": "vodka",
      "amount": "5",
      "measurement": "oz",
      "recipeId": 1,
      "id": 5
    },
    {
      "amount": "4",
      "measurement": "pinch",
      "label": "tabasco",
      "recipeId": 1,
      "id": 6
    },
    {
      "label": "honey",
      "amount": "1",
      "measurement": "tsp",
      "recipeId": 1,
      "id": 7
    },
    {
      "amount": "4",
      "measurement": "cups",
      "label": "cream",
      "recipeId": 1,
      "id": 8
    },
    {
      "recipeId": 15,
      "label": "flour",
      "amount": "2",
      "measurement": "cups",
      "id": 10
    },
    {
      "label": "sugar",
      "amount": "3",
      "measurement": "cups",
      "recipeId": 15,
      "id": 11
    },
    {
      "label": "molasses",
      "amount": "2",
      "measurement": "tbsp",
      "recipeId": 15,
      "id": 12
    },
    {
      "label": "brown sugar",
      "amount": "3",
      "measurement": "cups",
      "recipeId": 29,
      "id": 13
    },
    {
      "label": "blueberries",
      "amount": "3",
      "measurement": "cups",
      "recipeId": 30,
      "id": 14
    },
    {
      "recipeId": 20,
      "label": "sugar",
      "amount": "2",
      "measurement": "cups",
      "id": 15
    },
    {
      "label": "lemons",
      "amount": "4",
      "measurement": "oz",
      "recipeId": 20,
      "id": 16
    },
    {
      "recipeId": 6,
      "label": "chocolate chips",
      "amount": "4",
      "measurement": "cups",
      "id": 17
    },
    {
      "label": "whipped marshmallow",
      "amount": "24",
      "measurement": "oz",
      "recipeId": 31,
      "id": 18
    },
    {
      "recipeId": 10,
      "label": "powdered sugar",
      "amount": "2",
      "measurement": "cups",
      "id": 19
    },
    {
      "recipeId": 3,
      "label": "flour",
      "amount": "2",
      "measurement": "cups",
      "id": 20
    },
    {
      "label": "sugar",
      "amount": "2",
      "measurement": "cups",
      "recipeId": 3,
      "id": 21
    },
    {
      "recipeId": 4,
      "label": "bananas",
      "amount": "3",
      "measurement": "whole",
      "id": 22
    },
    {
      "recipeId": 5,
      "label": "chocolate chips",
      "amount": "2",
      "measurement": "bags",
      "id": 23
    },
    {
      "recipeId": 19,
      "label": "flour",
      "amount": "2",
      "measurement": "cups",
      "id": 24
    },
    {
      "label": "chocolate chips",
      "amount": "2",
      "measurement": "cups",
      "recipeId": 19,
      "id": 25
    },
    {
      "recipeId": 31,
      "label": "chocolate chips",
      "amount": "1",
      "measurement": "bags",
      "id": 26
    },
    {
      "label": "graham crackers",
      "amount": "24",
      "measurement": "pieces",
      "recipeId": 31,
      "id": 27
    },
    {
      "recipeId": 7,
      "label": "ginger",
      "amount": "2",
      "measurement": "tsp",
      "id": 28
    },
    {
      "label": "flour",
      "amount": "2",
      "measurement": "cups",
      "recipeId": 7,
      "id": 29
    },
    {
      "recipeId": 11,
      "label": "chopped chocolate",
      "amount": "2",
      "measurement": "quart",
      "id": 30
    },
    {
      "recipeId": 21,
      "label": "hazelnuts",
      "amount": "1",
      "measurement": "cup",
      "id": 31
    },
    {
      "recipeId": 25,
      "label": "chocolate chips",
      "amount": "3",
      "measurement": "bags",
      "id": 32
    },
    {
      "label": "sugar",
      "amount": "2",
      "measurement": "cups",
      "recipeId": 25,
      "id": 33
    },
    {
      "label": "sugar",
      "amount": "2",
      "measurement": "cups",
      "recipeId": 26,
      "id": 34
    },
    {
      "recipeId": 26,
      "label": "flour",
      "amount": "3",
      "measurement": "cups",
      "id": 35
    },
    {
      "label": "butter",
      "amount": "2",
      "measurement": "stick",
      "recipeId": 32,
      "id": 36
    },
    {
      "label": "hazelnuts (chopped)",
      "amount": "2",
      "measurement": "cups",
      "recipeId": 33,
      "id": 37
    },
    {
      "label": "sugar",
      "amount": "2",
      "measurement": "cups",
      "recipeId": 35,
      "id": 39
    },
    {
      "recipeId": 34,
      "label": "peach filling",
      "amount": "2",
      "measurement": "can(s)",
      "id": 40
    },
    {
      "label": "chocolate chips",
      "amount": "2",
      "measurement": "cups",
      "recipeId": 36,
      "id": 41
    },
    {
      "label": "sugar",
      "amount": "2",
      "measurement": "cups",
      "recipeId": 36,
      "id": 42
    },
    {
      "label": "flour",
      "amount": "2",
      "measurement": "cups",
      "recipeId": 36,
      "id": 43
    },
    {
      "recipeId": 12,
      "label": "egg",
      "amount": "1",
      "measurement": "whole",
      "id": 44
    },
    {
      "label": "sugar",
      "amount": "1/2",
      "measurement": "cup",
      "recipeId": 12,
      "id": 45
    },
    {
      "label": "sour cream",
      "amount": "6",
      "measurement": "oz",
      "recipeId": 12,
      "id": 46
    },
    {
      "label": "butter",
      "amount": "2",
      "measurement": "tbsp",
      "recipeId": 12,
      "id": 47
    },
    {
      "label": "flour",
      "amount": "2",
      "measurement": "cups",
      "recipeId": 12,
      "id": 48
    },
    {
      "recipeId": 32,
      "label": "flour",
      "amount": "3",
      "measurement": "cups",
      "id": 49
    },
    {
      "label": "sugar",
      "amount": "3",
      "measurement": "tbsp",
      "recipeId": 32,
      "id": 50
    },
    {
      "label": "warm milk",
      "amount": "1",
      "measurement": "cup",
      "recipeId": 32,
      "id": 51
    },
    {
      "label": "instant yeast",
      "amount": "1",
      "measurement": "package",
      "recipeId": 32,
      "id": 52
    }
  ],
  "images": [
    {
      "recipeId": 20,
      "image_path": "https://res.cloudinary.com/dllowdq2w/image/upload/v1644530377/8_rihh86.png",
      "id": 7
    },
    {
      "recipeId": 6,
      "image_path": "https://res.cloudinary.com/dllowdq2w/image/upload/v1644530460/6_oshv3f.png",
      "id": 8
    },
    {
      "recipeId": 31,
      "image_path": "https://res.cloudinary.com/dllowdq2w/image/upload/v1644530502/15_w1wo5u.png",
      "id": 9
    },
    {
      "recipeId": 30,
      "image_path": "https://res.cloudinary.com/dllowdq2w/image/upload/v1644531048/56_jc6qh8.png",
      "id": 10
    },
    {
      "recipeId": 1,
      "image_path": "https://res.cloudinary.com/dllowdq2w/image/upload/v1644531376/51_beke5e.png",
      "id": 11
    },
    {
      "recipeId": 29,
      "image_path": "https://res.cloudinary.com/dllowdq2w/image/upload/v1644531415/6_bwqcs1.png",
      "id": 12
    },
    {
      "recipeId": 10,
      "image_path": "https://res.cloudinary.com/dllowdq2w/image/upload/v1644531610/39_j3gboi.png",
      "id": 13
    },
    {
      "recipeId": 15,
      "image_path": "https://res.cloudinary.com/dllowdq2w/image/upload/v1644532190/gingercookies_aokcnl.png",
      "id": 14
    },
    {
      "recipeId": 2,
      "image_path": "https://res.cloudinary.com/dllowdq2w/image/upload/v1644532253/49_kqcazy.png",
      "id": 15
    },
    {
      "recipeId": 16,
      "image_path": "https://res.cloudinary.com/dllowdq2w/image/upload/v1644532307/4_pfajh3.png",
      "id": 16
    },
    {
      "recipeId": 3,
      "image_path": "https://res.cloudinary.com/dllowdq2w/image/upload/v1644532399/5_wo8ckq.png",
      "id": 17
    },
    {
      "recipeId": 17,
      "image_path": "https://res.cloudinary.com/dllowdq2w/image/upload/v1644532784/cupcakes_rsvlee.png",
      "id": 18
    },
    {
      "recipeId": 4,
      "image_path": "https://res.cloudinary.com/dllowdq2w/image/upload/v1644532842/61_m8cnrq.png",
      "id": 19
    },
    {
      "recipeId": 18,
      "image_path": "https://res.cloudinary.com/dllowdq2w/image/upload/v1644532939/75_xcjyef.png",
      "id": 20
    },
    {
      "recipeId": 18,
      "image_path": "https://res.cloudinary.com/dllowdq2w/image/upload/v1644533084/branmuffin_ehbkis.png",
      "id": 21
    },
    {
      "recipeId": 4,
      "image_path": "https://res.cloudinary.com/dllowdq2w/image/upload/v1644533196/61_vumiut.png",
      "id": 22
    },
    {
      "recipeId": 5,
      "image_path": "https://res.cloudinary.com/dllowdq2w/image/upload/v1644533239/46_zina3u.png",
      "id": 23
    },
    {
      "recipeId": 5,
      "image_path": "https://res.cloudinary.com/dllowdq2w/image/upload/v1644533363/46_rm5tl0.png",
      "id": 24
    },
    {
      "recipeId": 19,
      "image_path": "https://res.cloudinary.com/dllowdq2w/image/upload/v1644539915/extra_baked_goods_lwiu52.png",
      "id": 25
    },
    {
      "recipeId": 19,
      "image_path": "https://res.cloudinary.com/dllowdq2w/image/upload/v1644540002/extra_baked_goods_fpxmqy.png",
      "id": 26
    },
    {
      "recipeId": 31,
      "image_path": "https://res.cloudinary.com/dllowdq2w/image/upload/v1644540173/9_clpt9z.png",
      "id": 27
    },
    {
      "recipeId": 31,
      "image_path": "https://res.cloudinary.com/dllowdq2w/image/upload/v1644540361/smoresbars_irq1qk.png",
      "id": 28
    },
    {
      "recipeId": 10,
      "image_path": "https://res.cloudinary.com/dllowdq2w/image/upload/v1644540762/cookiefrosting_atbp8z.png",
      "id": 29
    },
    {
      "recipeId": 10,
      "image_path": "https://res.cloudinary.com/dllowdq2w/image/upload/v1644540846/cookiefrosting_nbzlzf.png",
      "id": 30
    },
    {
      "recipeId": 10,
      "image_path": "https://res.cloudinary.com/dllowdq2w/image/upload/v1644541613/icing_utglhw.jpg",
      "id": 31
    },
    {
      "recipeId": 10,
      "image_path": "https://res.cloudinary.com/dllowdq2w/image/upload/v1644542001/icing2_kanara.png",
      "id": 32
    },
    {
      "recipeId": 7,
      "image_path": "https://res.cloudinary.com/dllowdq2w/image/upload/v1644542079/11_mfe8ex.png",
      "id": 33
    },
    {
      "recipeId": 14,
      "image_path": "https://res.cloudinary.com/dllowdq2w/image/upload/v1644542426/coveredstrawberries_asqou1.png",
      "id": 34
    },
    {
      "recipeId": 8,
      "image_path": "https://res.cloudinary.com/dllowdq2w/image/upload/v1644542457/80_j6fcyp.png",
      "id": 35
    },
    {
      "recipeId": 9,
      "image_path": "https://res.cloudinary.com/dllowdq2w/image/upload/v1644542558/16_vjqi6y.png",
      "id": 36
    },
    {
      "recipeId": 13,
      "image_path": "https://res.cloudinary.com/dllowdq2w/image/upload/v1644545549/42_gnzw11.png",
      "id": 38
    },
    {
      "recipeId": 11,
      "image_path": "https://res.cloudinary.com/dllowdq2w/image/upload/v1644545643/35_xk9jg4.png",
      "id": 39
    },
    {
      "recipeId": 11,
      "image_path": "https://res.cloudinary.com/dllowdq2w/image/upload/v1644545738/35_hukqnf.png",
      "id": 40
    },
    {
      "recipeId": 21,
      "image_path": "https://res.cloudinary.com/dllowdq2w/image/upload/v1644545831/27_jwkil9.png",
      "id": 42
    },
    {
      "recipeId": 22,
      "image_path": "https://res.cloudinary.com/dllowdq2w/image/upload/v1644545888/72_fq9ca2.png",
      "id": 43
    },
    {
      "recipeId": 22,
      "image_path": "https://res.cloudinary.com/dllowdq2w/image/upload/v1644545902/88_me5ehl.png",
      "id": 44
    },
    {
      "recipeId": 23,
      "image_path": "https://res.cloudinary.com/dllowdq2w/image/upload/v1644545929/18_spa6ye.png",
      "id": 45
    },
    {
      "recipeId": 24,
      "image_path": "https://res.cloudinary.com/dllowdq2w/image/upload/v1644545969/26_hehi1a.png",
      "id": 46
    },
    {
      "recipeId": 25,
      "image_path": "https://res.cloudinary.com/dllowdq2w/image/upload/v1644546532/fudge_og5dfo.png",
      "id": 47
    },
    {
      "recipeId": 26,
      "image_path": "https://res.cloudinary.com/dllowdq2w/image/upload/v1644546698/desserts_b4jsh6.png",
      "id": 48
    },
    {
      "recipeId": 27,
      "image_path": "https://res.cloudinary.com/dllowdq2w/image/upload/v1644546754/45_schr88.png",
      "id": 49
    },
    {
      "recipeId": 32,
      "image_path": "https://res.cloudinary.com/dllowdq2w/image/upload/v1644547746/98_esf02y.png",
      "id": 60
    },
    {
      "recipeId": 33,
      "image_path": "https://res.cloudinary.com/dllowdq2w/image/upload/v1644548205/33_ubeo2v.png",
      "id": 51
    },
    {
      "recipeId": 34,
      "image_path": "https://res.cloudinary.com/dllowdq2w/image/upload/v1644548426/78_mvvveu.png",
      "id": 52
    },
    {
      "recipeId": 35,
      "image_path": "https://res.cloudinary.com/dllowdq2w/image/upload/v1644549297/12_hpqzjr.png",
      "id": 53
    },
    {
      "recipeId": 28,
      "image_path": "https://res.cloudinary.com/dllowdq2w/image/upload/v1644549437/cheesecake_lad6sn.png",
      "id": 54
    },
    {
      "recipeId": 36,
      "image_path": "https://res.cloudinary.com/dllowdq2w/image/upload/v1644550713/1_fzryeo.png",
      "id": 58
    },
    {
      "recipeId": 36,
      "image_path": "https://res.cloudinary.com/dllowdq2w/image/upload/v1644553179/2_owwi68.png",
      "id": 57
    },
    {
      "recipeId": 36,
      "image_path": "https://res.cloudinary.com/dllowdq2w/image/upload/v1644553285/5_o4armv.png",
      "id": 55
    },
    {
      "recipeId": 12,
      "image_path": "https://res.cloudinary.com/dllowdq2w/image/upload/v1644554460/10_lodv52.png",
      "id": 56
    },
    {
      "recipeId": 12,
      "image_path": "https://res.cloudinary.com/dllowdq2w/image/upload/v1644554594/4_nhzcka.png",
      "id": 59
    },
    {
      "recipeId": 32,
      "image_path": "https://res.cloudinary.com/dllowdq2w/image/upload/v1644554902/99_g5grie.png",
      "id": 50
    }
  ],
  "notes": [
    {
      "recipeId": 1,
      "text": "Add less sugar next time",
      "date": 1635611882958,
      "id": 1
    },
    {
      "recipeId": 1,
      "text": "Add more sugar next time",
      "date": 1635611882958,
      "id": 2
    },
    {
      "recipeId": 1,
      "text": "Next time bake an extra 5 minutes, it was a little teeny bit undercooked in the middle.",
      "date": 1635611882958,
      "id": 3
    }
  ],
  "items": [
    {
      "text": "whip cream",
      "userId": 1,
      "id": 1
    },
    {
      "text": "cream cheese",
      "userId": 1,
      "id": 2
    },
    {
      "text": "butter",
      "userId": 1,
      "id": 3
    },
    {
      "text": "love",
      "userId": 1,
      "id": 4
    }
  ],
  "ratings": [
    {
      "stars": "☆☆☆☆☆",
      "id": 1
    },
    {
      "stars": "★☆☆☆☆",
      "id": 2
    },
    {
      "stars": "★★☆☆☆",
      "id": 3
    },
    {
      "stars": "★★★☆☆",
      "id": 4
    },
    {
      "stars": "★★★★☆",
      "id": 5
    },
    {
      "stars": "★★★★★",
      "id": 6
    }
  ]
}